{
  "$schema": "https://developer.microsoft.com/json-schemas/fabric/item/report/definition/visualContainer/2.10.0/schema.json",
  "name": "82958966e56f41bbac72",
  "position": {
    "x": 779.96386961644191,
    "y": 70.576777065060867,
    "z": 3000,
    "height": 123.05694462625998,
    "width": 278.68778635947115,
    "tabOrder": 5000
  },
  "visual": {
    "visualType": "cardVisual",
    "query": {
      "queryState": {
        "Data": {
          "projections": [
            {
              "field": {
                "Measure": {
                  "Expression": {
                    "SourceRef": {
                      "Entity": "_Medidas"
                    }
                  },
                  "Property": "MTTR (horas)"
                }
              },
              "queryRef": "_Medidas.MTTR (horas)",
              "nativeQueryRef": "MTTR (horas)"
            }
          ]
        }
      }
    },
    "visualContainerObjects": {
      "title": [
        {
          "properties": {
            "show": {
              "expr": {
                "Literal": {
                  "Value": "true"
                }
              }
            },
            "text": {
              "expr": {
                "Literal": {
                  "Value": "'MTTR Médio (horas)'"
                }
              }
            }
          }
        }
      ]
    },
    "drillFilterOtherVisuals": true
  }
}